pynk2.cp312-win_amd64.pyd
libnk2_python-20240426.dist-info/METADATA
libnk2_python-20240426.dist-info/WHEEL
libnk2_python-20240426.dist-info/top_level.txt
libnk2_python-20240426.dist-info/RECORD
