Metadata-Version: 2.1
Name: libnk2-python
Version: 20240426
Summary: Python bindings module for libnk2
Author: Joachim Metz
Author-email: joachim.metz@gmail.com
License: GNU Lesser General Public License v3 or later (LGPLv3+)
Classifier: Development Status :: 3 - Alpha
Classifier: Programming Language :: Python
Requires-Python: >=3.7
